pintl/__init__.py
pintl/pintl.py
pintl-0.1.4.dist-info/LICENSE
pintl-0.1.4.dist-info/METADATA
pintl-0.1.4.dist-info/WHEEL
pintl-0.1.4.dist-info/top_level.txt
pintl-0.1.4.dist-info/RECORD
