Metadata-Version: 2.2
Name: pintl
Version: 0.1.4
Summary: A Python internationalization package
Author-email: Petri Lipponen <petri.lipponen@movesense.com>
License: MIT
Project-URL: Homepage, https://github.com/petri-lipponen-movesense/pintl
Project-URL: Repository, https://github.com/petri-lipponen-movesense/pintl
Classifier: Programming Language :: Python :: 3
Classifier: License :: OSI Approved :: MIT License
Classifier: Operating System :: OS Independent
Requires-Python: >=3.7
License-File: LICENSE
